ntt_ai_observability_exporter/__init__.py
ntt_ai_observability_exporter/semantic_kernel_telemetry.py
ntt_ai_observability_exporter/telemetry.py
ntt_ai_observability_exporter/telemetry_multi.py
ntt_ai_observability_exporter/utilities.py
ntt_ai_observability_exporter-0.2.9.dist-info/licenses/LICENSE
ntt_ai_observability_exporter-0.2.9.dist-info/METADATA
ntt_ai_observability_exporter-0.2.9.dist-info/WHEEL
ntt_ai_observability_exporter-0.2.9.dist-info/top_level.txt
ntt_ai_observability_exporter-0.2.9.dist-info/RECORD
