Metadata-Version: 2.4
Name: ntt-ai-observability-exporter
Version: 0.2.9
Summary: NTT AI Observability Exporter for Azure Monitor OpenTelemetry in AI Foundry projects
Author-email: Anand Vaibhav Singh <anandvaibhav-singh_nttltd@example.com>
License: MIT
Project-URL: Homepage, https://github.com/nttlimited/ntt-ai-observability-exporter
Project-URL: Bug Tracker, https://github.com/nttlimited/ntt-ai-observability-exporter/issues
Keywords: ntt,azure,telemetry,opentelemetry,monitoring,ai,observability
Classifier: Programming Language :: Python :: 3
Classifier: License :: OSI Approved :: MIT License
Classifier: Operating System :: OS Independent
Classifier: Development Status :: 4 - Beta
Classifier: Intended Audience :: Developers
Classifier: Topic :: Software Development :: Libraries :: Python Modules
Requires-Python: >=3.8
License-File: LICENSE
Requires-Dist: azure-monitor-opentelemetry>=1.6.7
Requires-Dist: azure-core-tracing-opentelemetry>=1.0.0b12
Requires-Dist: langchain_azure_ai>=0.1.5
Requires-Dist: opentelemetry-sdk>=1.31.1
Requires-Dist: azure-monitor-opentelemetry-exporter>=1.0.0b37
Requires-Dist: opentelemetry-api>=1.15.0
Requires-Dist: opentelemetry-instrumentation>=0.38b0
Provides-Extra: dev
Requires-Dist: pytest>=7.0.0; extra == "dev"
Requires-Dist: pytest-mock>=3.8.0; extra == "dev"
Requires-Dist: pytest-cov>=4.0.0; extra == "dev"
Requires-Dist: black>=22.3.0; extra == "dev"
Requires-Dist: flake8>=4.0.1; extra == "dev"
Requires-Dist: mypy>=0.950; extra == "dev"
Requires-Dist: isort>=5.10.1; extra == "dev"
Requires-Dist: build>=0.8.0; extra == "dev"
Requires-Dist: twine>=4.0.0; extra == "dev"
Provides-Extra: test
Requires-Dist: pytest>=7.0.0; extra == "test"
Requires-Dist: pytest-mock>=3.8.0; extra == "test"
Requires-Dist: pytest-cov>=4.0.0; extra == "test"
Provides-Extra: databases
Requires-Dist: opentelemetry-instrumentation-psycopg2>=0.38b0; extra == "databases"
Requires-Dist: opentelemetry-instrumentation-pyodbc>=0.38b0; extra == "databases"
Requires-Dist: opentelemetry-instrumentation-pymysql>=0.38b0; extra == "databases"
Requires-Dist: opentelemetry-instrumentation-sqlite3>=0.38b0; extra == "databases"
Requires-Dist: opentelemetry-instrumentation-sqlalchemy>=0.38b0; extra == "databases"
Requires-Dist: opentelemetry-instrumentation-redis>=0.38b0; extra == "databases"
Requires-Dist: opentelemetry-instrumentation-pymongo>=0.38b0; extra == "databases"
Provides-Extra: azure-databases
Requires-Dist: opentelemetry-instrumentation-psycopg2>=0.38b0; extra == "azure-databases"
Requires-Dist: opentelemetry-instrumentation-pyodbc>=0.38b0; extra == "azure-databases"
Requires-Dist: opentelemetry-instrumentation-pymongo>=0.38b0; extra == "azure-databases"
Provides-Extra: all
Requires-Dist: opentelemetry-instrumentation-psycopg2>=0.38b0; extra == "all"
Requires-Dist: opentelemetry-instrumentation-pyodbc>=0.38b0; extra == "all"
Requires-Dist: opentelemetry-instrumentation-pymysql>=0.38b0; extra == "all"
Requires-Dist: opentelemetry-instrumentation-sqlite3>=0.38b0; extra == "all"
Requires-Dist: opentelemetry-instrumentation-sqlalchemy>=0.38b0; extra == "all"
Requires-Dist: opentelemetry-instrumentation-redis>=0.38b0; extra == "all"
Requires-Dist: opentelemetry-instrumentation-pymongo>=0.38b0; extra == "all"
Dynamic: license-file
